pocketvec/__init__.py
pocketvec/core.py
pocketvec/io_utils.py
pocketvec/similarity.py
pocketvec-0.1.2.dist-info/licenses/LICENSE.txt
pocketvec-0.1.2.dist-info/METADATA
pocketvec-0.1.2.dist-info/WHEEL
pocketvec-0.1.2.dist-info/top_level.txt
pocketvec-0.1.2.dist-info/RECORD
