Metadata-Version: 2.4
Name: pocketvec
Version: 0.1.2
Summary: A lightweight vector store built on SentenceTransformers
Author-email: Parupudi Raghava Krishna Pramod <prkpramod98@gmail.com>
License: MIT
Project-URL: Homepage, https://github.com/KrishnaPramodParupudi/pocketvec
Project-URL: Repository, https://github.com/KrishnaPramodParupudi/pocketvec
Project-URL: Issues, https://github.com/KrishnaPramodParupudi/pocketvec/issues
Requires-Python: >=3.8
License-File: LICENSE.txt
Requires-Dist: numpy<3.0,>=2.3
Requires-Dist: sentence-transformers<6.0,>=5.1
Requires-Dist: huggingface-hub<1.0,>=0.34
Dynamic: license-file
